fixtureupper
