Metadata-Version: 1.1
Name: fixtureupper
Version: 0.2.7
Summary: SqlAlchemy Fixture Generator
Home-page: https://github.com/Rhathe/fixtureupper
Author: Ramon Sandoval
Author-email: UNKNOWN
License: MIT
Platform: UNKNOWN
Classifier: Development Status :: 3 - Alpha
Classifier: Intended Audience :: Developers
Classifier: License :: OSI Approved :: MIT License
Classifier: Programming Language :: Python :: 2.7
Classifier: Programming Language :: Python :: 3.4
Classifier: Programming Language :: Python :: 3.5
Classifier: Topic :: Utilities
